HyresRebuilder/Rebuilder.py
HyresRebuilder/Rotamer.py
HyresRebuilder/__init__.py
HyresRebuilder/__main__.py
HyresRebuilder/base.py
HyresRebuilder/map/ALA_ideal.pdb
HyresRebuilder/map/ARG_ideal.pdb
HyresRebuilder/map/ASN_ideal.pdb
HyresRebuilder/map/ASP_ideal.pdb
HyresRebuilder/map/CYS_ideal.pdb
HyresRebuilder/map/GLN_ideal.pdb
HyresRebuilder/map/GLU_ideal.pdb
HyresRebuilder/map/GLY_ideal.pdb
HyresRebuilder/map/HIS_ideal.pdb
HyresRebuilder/map/ILE_ideal.pdb
HyresRebuilder/map/LEU_ideal.pdb
HyresRebuilder/map/LYS_ideal.pdb
HyresRebuilder/map/MET_ideal.pdb
HyresRebuilder/map/PHE_ideal.pdb
HyresRebuilder/map/PRO_ideal.pdb
HyresRebuilder/map/SER_ideal.pdb
HyresRebuilder/map/THR_ideal.pdb
HyresRebuilder/map/TRP_ideal.pdb
HyresRebuilder/map/TYR_ideal.pdb
HyresRebuilder/map/VAL_ideal.pdb
HyresRebuilder-0.4.5.dist-info/LICENSE
HyresRebuilder-0.4.5.dist-info/METADATA
HyresRebuilder-0.4.5.dist-info/WHEEL
HyresRebuilder-0.4.5.dist-info/entry_points.txt
HyresRebuilder-0.4.5.dist-info/top_level.txt
HyresRebuilder-0.4.5.dist-info/RECORD
